{
	"credit": "Made with Blockbench",
	"parent": "minecraft:block/block",
	"render_type": "minecraft:cutout",
	"textures": {
		"0": "gsr_yatm:block/device/tank/ends",
		"1": "gsr_yatm:block/device/tank/side",
		"particle": "gsr_yatm:block/device/tank/ends"
	},
		"elements": [
		{
			"from": [2, 0, 2],
			"to": [14, 1, 14],
			"faces": {
				"north": {"uv": [2, 15, 14, 16], "texture": "#1"},
				"east": {"uv": [2, 15, 14, 16], "texture": "#1"},
				"south": {"uv": [2, 15, 14, 16], "texture": "#1"},
				"west": {"uv": [2, 15, 14, 16], "texture": "#1"},
				"up": {"uv": [2, 2, 14, 14], "texture": "#0"},
				"down": {"uv": [2, 2, 14, 14], "texture": "#0"}
			}
		},
		{
			"from": [2, 15, 2],
			"to": [14, 16, 14],
			"faces": {
				"north": {"uv": [2, 0, 14, 1], "texture": "#1"},
				"east": {"uv": [2, 0, 14, 1], "texture": "#1"},
				"south": {"uv": [2, 0, 14, 1], "texture": "#1"},
				"west": {"uv": [2, 0, 14, 1], "texture": "#1"},
				"up": {"uv": [2, 2, 14, 14], "texture": "#0"},
				"down": {"uv": [2, 2, 14, 14], "texture": "#0"}
			}
		},
		{
			"from": [2, 1, 2],
			"to": [4, 15, 3],
			"faces": {
				"north": {"uv": [12, 1, 14, 15], "texture": "#1"},
				"east": {"uv": [3, 1, 4, 15], "texture": "#1"},
				"south": {"uv": [2, 1, 4, 15], "texture": "#1"},
				"west": {"uv": [2, 1, 3, 15], "texture": "#1"}
			}
		},
		{
			"from": [12, 1, 2],
			"to": [14, 15, 3],
			"faces": {
				"north": {"uv": [2, 1, 4, 15], "texture": "#1"},
				"east": {"uv": [13, 1, 14, 15], "texture": "#1"},
				"south": {"uv": [12, 1, 14, 15], "texture": "#1"},
				"west": {"uv": [3, 1, 4, 15], "texture": "#1"}
			}
		},
		{
			"from": [12, 1, 13],
			"to": [14, 15, 14],
			"faces": {
				"north": {"uv": [11, 1, 13, 15], "texture": "#1"},
				"east": {"uv": [2, 1, 3, 15], "texture": "#1"},
				"south": {"uv": [12, 1, 14, 15], "texture": "#1"},
				"west": {"uv": [12, 1, 13, 15], "texture": "#1"}
			}
		},
		{
			"from": [2, 1, 13],
			"to": [4, 15, 14],
			"faces": {
				"north": {"uv": [3, 1, 5, 15], "texture": "#1"},
				"east": {"uv": [12, 1, 13, 15], "texture": "#1"},
				"south": {"uv": [2, 1, 4, 15], "texture": "#1"},
				"west": {"uv": [13, 1, 14, 15], "texture": "#1"}
			}
		},
		{
			"from": [2, 1, 3],
			"to": [3, 15, 4],
			"faces": {
				"east": {"uv": [12, 1, 13, 15], "texture": "#1"},
				"south": {"uv": [12, 1, 13, 15], "texture": "#1"},
				"west": {"uv": [3, 1, 4, 15], "texture": "#1"}
			}
		},
		{
			"from": [13, 1, 3],
			"to": [14, 15, 4],
			"faces": {
				"east": {"uv": [12, 1, 13, 15], "texture": "#1"},
				"south": {"uv": [3, 1, 4, 15], "texture": "#1"},
				"west": {"uv": [12, 1, 13, 15], "texture": "#1"}
			}
		},
		{
			"from": [13, 1, 12],
			"to": [14, 15, 13],
			"faces": {
				"north": {"uv": [3, 1, 4, 15], "texture": "#1"},
				"east": {"uv": [3, 1, 4, 15], "texture": "#1"},
				"west": {"uv": [3, 1, 4, 15], "texture": "#1"}
			}
		},
		{
			"from": [2, 1, 12],
			"to": [3, 15, 13],
			"faces": {
				"north": {"uv": [12, 1, 13, 15], "texture": "#1"},
				"east": {"uv": [3, 1, 4, 15], "texture": "#1"},
				"west": {"uv": [12, 1, 13, 15], "texture": "#1"}
			}
		},
		{
			"from": [4, 14, 2],
			"to": [12, 15, 3],
			"faces": {
				"north": {"uv": [4, 1, 12, 2], "texture": "#1"},
				"south": {"uv": [4, 1, 12, 2], "texture": "#1"},
				"down": {"uv": [4, 1, 12, 2], "texture": "#1"}
			}
		},
		{
			"from": [4, 14, 13],
			"to": [12, 15, 14],
			"faces": {
				"north": {"uv": [4, 1, 12, 2], "texture": "#1"},
				"south": {"uv": [4, 1, 12, 2], "texture": "#1"},
				"west": {"uv": [0, 0, 1, 1], "texture": "#1"},
				"down": {"uv": [4, 1, 12, 2], "texture": "#1"}
			}
		},
		{
			"from": [13, 14, 4],
			"to": [14, 15, 12],
			"faces": {
				"east": {"uv": [4, 1, 12, 2], "texture": "#1"},
				"west": {"uv": [4, 1, 12, 2], "texture": "#1"},
				"down": {"uv": [4, 1, 12, 2], "rotation": 270, "texture": "#1"}
			}
		},
		{
			"from": [2, 14, 4],
			"to": [3, 15, 12],
			"faces": {
				"east": {"uv": [4, 1, 12, 2], "texture": "#1"},
				"west": {"uv": [4, 1, 12, 2], "texture": "#1"},
				"down": {"uv": [4, 1, 12, 2], "rotation": 270, "texture": "#1"}
			}
		},
		{
			"from": [4, 1, 2],
			"to": [12, 2, 3],
			"faces": {
				"north": {"uv": [4, 14, 12, 15], "texture": "#1"},
				"south": {"uv": [4, 14, 12, 15], "texture": "#1"},
				"up": {"uv": [4, 14, 12, 15], "texture": "#1"}
			}
		},
		{
			"from": [4, 1, 13],
			"to": [12, 2, 14],
			"faces": {
				"north": {"uv": [4, 14, 12, 15], "texture": "#1"},
				"south": {"uv": [4, 14, 12, 15], "texture": "#1"},
				"west": {"uv": [0, 0, 1, 1], "texture": "#1"},
				"up": {"uv": [4, 14, 12, 15], "texture": "#1"}
			}
		},
		{
			"from": [13, 1, 4],
			"to": [14, 2, 12],
			"faces": {
				"east": {"uv": [4, 14, 12, 15], "texture": "#1"},
				"west": {"uv": [4, 14, 12, 15], "texture": "#1"},
				"up": {"uv": [4, 14, 12, 15], "rotation": 90, "texture": "#1"}
			}
		},
		{
			"from": [2, 1, 4],
			"to": [3, 2, 12],
			"faces": {
				"east": {"uv": [4, 14, 12, 15], "texture": "#1"},
				"west": {"uv": [4, 14, 12, 15], "texture": "#1"},
				"up": {"uv": [4, 14, 12, 15], "rotation": 90, "texture": "#1"}
			}
		},
		{
			"from": [4, 2, 2],
			"to": [12, 14, 2],
			"faces": {
				"north": {"uv": [4, 2, 12, 14], "texture": "#1"},
				"south": {"uv": [4, 2, 12, 14], "texture": "#1"}
			}
		},
		{
			"from": [4, 2, 14],
			"to": [12, 14, 14],
			"faces": {
				"north": {"uv": [4, 2, 12, 14], "texture": "#1"},
				"south": {"uv": [4, 2, 12, 14], "texture": "#1"}
			}
		},
		{
			"from": [2, 2, 4],
			"to": [2, 14, 12],
			"faces": {
				"east": {"uv": [4, 2, 12, 14], "texture": "#1"},
				"west": {"uv": [4, 2, 12, 14], "texture": "#1"}
			}
		},
		{
			"from": [14, 2, 4],
			"to": [14, 14, 12],
			"faces": {
				"east": {"uv": [4, 2, 12, 14], "texture": "#1"},
				"west": {"uv": [4, 2, 12, 14], "texture": "#1"}
			}
		}
	]
}